GoDebian_api-1.1.0.dev1.dist-info/WHEEL
GoDebian_api-1.1.0.dev1.dist-info/top_level.txt
GoDebian_api-1.1.0.dev1.dist-info/metadata.json
GoDebian_api-1.1.0.dev1.dist-info/RECORD
GoDebian_api-1.1.0.dev1.dist-info/DESCRIPTION.rst
GoDebian_api-1.1.0.dev1.dist-info/METADATA
GoDebian/__init__.py
GoDebian/api.py
