Metadata-Version: 2.0
Name: GoDebian-api
Version: 1.1.0.dev1
Summary: Python client for go.debian.net and deb.li URL shortening service
Home-page: https://github.com/ninjatrench/GoDebian_api
Author: Harsh Daftary
Author-email: info@securitylabs.in
License: MIT
Download-URL: https://github.com/ninjatrench/GoDebian_api/tarball/master
Platform: UNKNOWN
Classifier: Development Status :: 4 - Beta
Classifier: Intended Audience :: Developers
Classifier: License :: OSI Approved :: MIT License
Classifier: Programming Language :: Python :: 2
Classifier: Programming Language :: Python :: 2.6
Classifier: Programming Language :: Python :: 2.7
Classifier: Programming Language :: Python :: 3
Classifier: Programming Language :: Python :: 3.2
Classifier: Programming Language :: Python :: 3.3
Classifier: Programming Language :: Python :: 3.4
Classifier: Topic :: Software Development :: Libraries :: Python Modules
Requires-Dist: requests
